{
  "Fire": {
    "Outgoing": {
      "Normal": 1,
      "Fire": 0.5,
      "Water": 0.5,
      "Electric": 1,
      "Grass": 2,
      "Ice": 2,
      "Fighting": 1,
      "Poison": 1,
      "Ground": 1,
      "Flying": 1,
      "Psychic": 1,
      "Bug": 2,
      "Rock": 0.5,
      "Ghost": 1,
      "Dragon": 0.5,
      "Dark": 1,
      "Steel": 2,
      "Fairy": 1,

      "Normal/Fire": 0.5,
      "Normal/Water": 0.5,
      "Normal/Electric": 1,
      "Normal/Grass": 2,
      "Normal/Ice": 2,
      "Normal/Fighting": 1,
      "Normal/Poison": 1,
      "Normal/Ground": 1,
      "Normal/Flying": 1,
      "Normal/Psychic": 1,
      "Normal/Bug": 2,
      "Normal/Rock": 0.5,
      "Normal/Ghost": 1,
      "Normal/Dragon": 0.5,
      "Normal/Dark": 1,
      "Normal/Steel": 2,
      "Normal/Fairy": 1,

      "Fire/Water": 0.25,
      "Fire/Electric": 0.5,
      "Fire/Grass": 1,
      "Fire/Ice": 1,
      "Fire/Fighting": 0.5,
      "Fire/Poison": 0.5,
      "Fire/Ground": 0.5,
      "Fire/Flying": 0.5,
      "Fire/Psychic": 0.5,
      "Fire/Bug": 1,
      "Fire/Rock": 0.25,
      "Fire/Ghost": 0.5,
      "Fire/Dragon": 0.25,
      "Fire/Dark": 0.5,
      "Fire/Steel": 1,
      "Fire/Fairy": 0.5,

      "Water/Electric": 0.5,
      "Water/Grass": 1,
      "Water/Ice": 1,
      "Water/Fighting": 0.5,
      "Water/Poison": 0.5,
      "Water/Ground": 0.5,
      "Water/Flying": 0.5,
      "Water/Psychic": 0.5,
      "Water/Bug": 1,
      "Water/Rock": 0.25,
      "Water/Ghost": 0.5,
      "Water/Dragon": 0.25,
      "Water/Dark": 0.5,
      "Water/Steel": 1,
      "Water/Fairy": 0.5,

      "Electric/Grass": 2,
      "Electric/Ice": 2,
      "Electric/Fighting": 1,
      "Electric/Poison": 1,
      "Electric/Ground": 1,
      "Electric/Flying": 1,
      "Electric/Psychic": 1,
      "Electric/Bug": 2,
      "Electric/Rock": 0.5,
      "Electric/Ghost": 1,
      "Electric/Dragon": 0.5,
      "Electric/Dark": 1,
      "Electric/Steel": 2,
      "Electric/Fairy": 1,

      "Grass/Ice": 4,
      "Grass/Fighting": 2,
      "Grass/Poison": 2,
      "Grass/Ground": 2,
      "Grass/Flying": 2,
      "Grass/Psychic": 2,
      "Grass/Bug": 4,
      "Grass/Rock": 1,
      "Grass/Ghost": 2,
      "Grass/Dragon": 1,
      "Grass/Dark": 2,
      "Grass/Steel": 4,
      "Grass/Fairy": 2,

      "Ice/Fighting": 2,
      "Ice/Poison": 2,
      "Ice/Ground": 2,
      "Ice/Flying": 2,
      "Ice/Psychic": 2,
      "Ice/Bug": 4,
      "Ice/Rock": 1,
      "Ice/Ghost": 2,
      "Ice/Dragon": 1,
      "Ice/Dark": 2,
      "Ice/Steel": 4,
      "Ice/Fairy": 2,

      "Fighting/Poison": 1,
      "Fighting/Ground": 1,
      "Fighting/Flying": 1,
      "Fighting/Psychic": 1,
      "Fighting/Bug": 2,
      "Fighting/Rock": 0.5,
      "Fighting/Ghost": 1,
      "Fighting/Dragon": 0.5,
      "Fighting/Dark": 1,
      "Fighting/Steel": 2,
      "Fighting/Fairy": 1,

      "Poison/Ground": 1,
      "Poison/Flying": 1,
      "Poison/Psychic": 1,
      "Poison/Bug": 2,
      "Poison/Rock": 0.5,
      "Poison/Ghost": 1,
      "Poison/Dragon": 0.5,
      "Poison/Dark": 1,
      "Poison/Steel": 2,
      "Poison/Fairy": 1,

      "Ground/Flying": 1,
      "Ground/Psychic": 1,
      "Ground/Bug": 2,
      "Ground/Rock": 0.5,
      "Ground/Ghost": 1,
      "Ground/Dragon": 0.5,
      "Ground/Dark": 1,
      "Ground/Steel": 2,
      "Ground/Fairy": 1,

      "Flying/Psychic": 1,
      "Flying/Bug": 2,
      "Flying/Rock": 0.5,
      "Flying/Ghost": 1,
      "Flying/Dragon": 0.5,
      "Flying/Dark": 1,
      "Flying/Steel": 2,
      "Flying/Fairy": 1,

      "Psychic/Bug": 2,
      "Psychic/Rock": 0.5,
      "Psychic/Ghost": 1,
      "Psychic/Dragon": 0.5,
      "Psychic/Dark": 1,
      "Psychic/Steel": 2,
      "Psychic/Fairy": 1,

      "Bug/Rock": 1,
      "Bug/Ghost": 2,
      "Bug/Dragon": 1,
      "Bug/Dark": 2,
      "Bug/Steel": 4,
      "Bug/Fairy": 2,

      "Rock/Ghost": 0.5,
      "Rock/Dragon": 0.25,
      "Rock/Dark": 0.5,
      "Rock/Steel": 1,
      "Rock/Fairy": 0.5,

      "Ghost/Dragon": 0.5,
      "Ghost/Dark": 1,
      "Ghost/Steel": 2,
      "Ghost/Fairy": 1,

      "Dragon/Dark": 0.5,
      "Dragon/Steel": 1,
      "Dragon/Fairy": 0.5,

      "Dark/Steel": 2,
      "Dark/Fairy": 1,

      "Steel/Fairy": 2
    }
  }
}